legalopsrag/.DS_Store
legalopsrag/azure/blob_storage.py
legalopsrag/controllers/word_pluging.py
legalopsrag/database/mongo_db.py
legalopsrag/embeddings/vogayeai.py
legalopsrag/prompts/contract_review.txt
legalopsrag/prompts/extract_legal_clause.txt
legalopsrag/prompts/review_legal_clause.txt
legalopsrag/retrievers/mongodb_retriever.py
legalopsrag/retrievers/retriever_general.py
legalopsrag/splitter/spacy_splitter.py
legalopsrag/utils/utils_func.py
legalopsrag-0.7.0.dist-info/METADATA
legalopsrag-0.7.0.dist-info/WHEEL
legalopsrag-0.7.0.dist-info/RECORD
