Metadata-Version: 2.1
Name: legalopsrag
Version: 0.7.0
Summary: legalsops for retriever and reader
Author: Victor Venegas
Author-email: dextex@hotmail.com
Requires-Python: ==3.10.*
Classifier: Programming Language :: Python :: 3
Classifier: Programming Language :: Python :: 3.10
Requires-Dist: anthropic (>=0.34.2,<0.35.0)
Requires-Dist: azure-identity (>=1.18.0,<2.0.0)
Requires-Dist: azure-storage-blob (>=12.23.1,<13.0.0)
Requires-Dist: dspy-ai (==2.4.13)
Requires-Dist: flask (>=3.0.3,<4.0.0)
Requires-Dist: flask-cors (>=5.0.0,<6.0.0)
Requires-Dist: langchain (>=0.3.0,<0.4.0)
Requires-Dist: langchain-voyageai (>=0.1.1,<0.2.0)
Requires-Dist: pymongo (>=4.8.0,<5.0.0)
Requires-Dist: pytest (==7.1)
Requires-Dist: pytest-asyncio (==0.21.0)
Requires-Dist: python-dotenv (>=1.0.1,<2.0.0)
